{"projectRoot": "/Users/ssfak/Documents/01-github/ar", "batchFiles": [{"path": "docs/db-design.html", "language": "html", "sizeLines": 1121, "fileCategory": "markup"}, {"path": "docs/deploy.md", "language": "markdown", "sizeLines": 166, "fileCategory": "docs"}, {"path": "docs/futsal_rulebook_db_apply_guide.md", "language": "markdown", "sizeLines": 180, "fileCategory": "docs"}, {"path": "docs/harness-system-analysis.html", "language": "html", "sizeLines": 1279, "fileCategory": "markup"}, {"path": "docs/mvp-roadmap.html", "language": "html", "sizeLines": 574, "fileCategory": "markup"}, {"path": "docs/privacy-policy.html", "language": "html", "sizeLines": 396, "fileCategory": "markup"}, {"path": "docs/project-current-map.html", "language": "html", "sizeLines": 718, "fileCategory": "markup"}, {"path": "docs/store-listing.md", "language": "markdown", "sizeLines": 128, "fileCategory": "docs"}, {"path": "docs/team-collaboration.md", "language": "markdown", "sizeLines": 137, "fileCategory": "docs"}, {"path": "docs/team-onboarding.html", "language": "html", "sizeLines": 844, "fileCategory": "markup"}, {"path": "docs/test-account-setup.md", "language": "markdown", "sizeLines": 73, "fileCategory": "docs"}], "batchImportData": {"docs/db-design.html": [], "docs/deploy.md": [], "docs/futsal_rulebook_db_apply_guide.md": [], "docs/harness-system-analysis.html": [], "docs/mvp-roadmap.html": [], "docs/privacy-policy.html": [], "docs/project-current-map.html": [], "docs/store-listing.md": [], "docs/team-collaboration.md": [], "docs/team-onboarding.html": [], "docs/test-account-setup.md": []}}